{
  "name": "Cory Willis",
  "age": 46,
  "address": {
    "street": "Jenati Mill",
    "city": "Ucuvagi",
    "state": "ID",
    "zip": "39062"
  },
  "contact": {
    "phone": "(612) 651-4468",
    "servicePhone": "800479636"
  },
  "birthday": "1993-03-06T10:54:05.167Z",
  "ip": "162.99.104.7",
  "foo": "bar",
  "profile": {
    "about": "Evoci def cidci revfow mehor picaj kiv guzzeja oremuzu un gip et hifpubran. Celtuf zaggare ebnonezi denlomzu cehujfe da ecbad kuwgu su lohjaz zacatto fi filzevu gawicuz us. Kas mad efihaf zeca vakuche avneami teziw muav kes rucih belivane dikiat. Segpid or gezin awewa tun taz bopif ifrag poj corigon gurusemi hajzeira meburdiz kohpo mejmar. Dal puisi mudakiv wec jemmima fejhawti re fijugte nodmadut lemana tak catdac ik voncu takenfug gobpu ridtuob.",
    "bio": "Nimajbu kecovfa zuc lezkinpo per sofeutu dan liomimo vosba da pow ezides no di zimoviz jafepse foibuwu. Dohhenof ubiizri ovihib uwihoezu henap nasow tenvecge nuh be epaucu gofva recmoncab jo befoj ani. Dief napvow ahnen kajaas leh wubba puvejfiw adonu oratutha riwap ice elenam larjowni adpajut amsablov re bafamwa ze. Dudugu pe fi herdo ba fero suzvul wubmicwac zuola wo dinke are gun cic. Cis joopoiro didjajip ze uwa imteg lurtefav sedil eda duk guc volu ahahe mudmi ga tobsis ufi ugesesru."
  },
  "apiKey": "28c95dc2cc0d354782a8e55d93a9b6e16edb453a52844e37b27a96035fae69e9",
  "currency": {
    "code": "BOB",
    "name": "Bolivia Boliviano"
  }
}