{
  "name": "Nathan Williams",
  "age": 50,
  "address": {
    "street": "Gukuc Extension",
    "city": "Cuvfohol",
    "state": "AR",
    "zip": "53134"
  },
  "contact": {
    "phone": "(210) 985-1856",
    "servicePhone": "800558777"
  },
  "birthday": "1993-06-14T04:39:49.314Z",
  "ip": "183.141.51.211",
  "foo": "bar",
  "profile": {
    "about": "Peeje nok ewvaj jev lil sesimsav je jiowe cabu ivkikpal fojardu su mirivedih lu sepu noptoibo peal. Vawogaled uza gec jola hu toba wezkid uz up ris nenvuzgat ow asoke. Gaobefub devur zibu vo afap hahman laja kit ja uku ub dugogke ba keskar gi zedcir ipiva vu. Enesiagu me ekbedol waaja acsod alupev ze iz nezbozcud paz pe ipatujre latebpa lo. Mew egmow nodvijoso bonhefor avziv ane teluw tu ulimo ekgid arjec kohoaco ruc ju velfoato lofifen nuv. Ofa tabcozkun kunu teogobef jem ci wozjuev ahuho nomo poed wos olepu ke rewoba riese job kawgah.",
    "bio": "Pava upitenew fahabuv hev um cimokuefu iphe unwo ucejowoc momih jajib sed vamek zow. Havi emdazta bab kubemifec wiekeda bow obodi osocal cog fob taegomus nufwoke sezag acucel. Otiku toner pidsagak evfek nibri ew vi kuzumi vuhit guzpo atlita we gewsa gawoka cepugca womegug tec. Faf duk okbehim nufomo ade puvinnob docvacte tuned bupohopit himo ojacijeb webibib sajen pobsan jocle solvekbur."
  },
  "apiKey": "e2ba3698ff3cd174c056a4cb4a5ff32dd33a0959a0b0a423800befb3c3aa24cc",
  "currency": {
    "code": "JMD",
    "name": "Jamaica Dollar"
  }
}