{
  "name": "Louis Klein",
  "age": 38,
  "address": {
    "street": "Oziore Parkway",
    "city": "Ucasibus",
    "state": "OK",
    "zip": "72490"
  },
  "contact": {
    "phone": "(551) 460-5796",
    "servicePhone": "800117359"
  },
  "birthday": "1998-12-26T03:11:24.316Z",
  "ip": "32.218.26.142",
  "foo": "bar",
  "profile": {
    "about": "Vijmaw zig bibatvil zaate hiub urniwbi pesate ta gepbeg gaar larnisto tiz goshiwvuc. Padzaz con bul iso zapowuh dub pijparlot ehwewlos ne ebcas upo nedobise pan. Tedvu fafem ohojubma ilucuh me wap lawlomod ojvud nuorugo beemulup te pev gev vobo. Tuvuge powi ececu ahut sesikiw metgoid givfuknuz facorufif gidmojfow hivvewuv rehcolav aha kazwejhas tad puajasim.",
    "bio": "Nofif nuhebwem peodima woajzu mazhemlo pilujo sepcandu ehi diz jewu wanbabop natiat pas luofrul vatotnit. Guru kehehcu zawoh ucza decgobso avu hebovbi vuhpivi buz wostefte fav si. Citawuac zilpadulo numig lucarom zaji bo wurwos uzpep vez zulcerot hakpu hiwku uja loapu lavfugsu. Kuppe wopoc vior offi totunwo dootewog giafeze na wu runob ec so moomi. Nemmohpin dizcasi civpez onlo bu hohjushig ema tinlu we dowvofub bi nefita sevzalpus. Opudan sif ola purbaw le gac nave wej tifgaot ubuasget pocuco kom kupouvu ujoumi tepedup uzekivmip jicojme. Nug vewid natvuac ik biziro bivdemvi wiivhof pabtat lamiguje kibhip zerwu iju pol rulihnoj em cesguj gognihrul."
  },
  "apiKey": "0fb7d617758f839d1059fef4a36e866eec073121656338e147103073b47042b6",
  "currency": {
    "code": "SOS",
    "name": "Somalia Shilling"
  }
}