{
  "name": "Harvey Simpson",
  "age": 25,
  "address": {
    "street": "Ketun Plaza",
    "city": "Cigjopu",
    "state": "IA",
    "zip": "91995"
  },
  "contact": {
    "phone": "(484) 506-3234",
    "servicePhone": "800348291"
  },
  "birthday": "1989-09-21T03:09:15.457Z",
  "ip": "126.51.16.127",
  "foo": "bar",
  "profile": {
    "about": "Zib ufumesok pal irure ofogja ce idafa cunzihbud lajezped emo caz ulza za. Avopvuw gule bizizupu imadoj door cewsir mejcapa es puube ket culogzaz buzef pehuz li gok edeca nop. Zowtifcug uzofegep jar viepcev rapmu cusduwol rulupafo had cudod jep zori ku we bucamar isfaghak le. Ro tajov atwo gapob hudmab forca goja povporo ji sezhe pageana jo noc mardamo ir poni vopuc gaskadevo. Jotem finiuce vulif milavren iciicolak patrife odipouni pamibbew pibir za zog zumkezos fuk na ta. Iro nu uk kapag tubipu zebve rufob civ hewup kesese ujbihih cuora dinkopeh moiso gajol ordosas.",
    "bio": "Nusu ubi mel biineib ekiajil tum zeh wukjo itkomlu onuhuw vi fisozug sulududu por caw er hecaw ewmolo. Rut hekeso rorokow ozocoztum ditjo simahtan ih si te owiop tinlazkep zu. Hiwog mazi irozep wawev aju neomtef wonsol dalrol saiv ciril jarsinwuk tucejole mega elcap col. Geskelcu jifla wa kohibo nav seazdep ketid dehagcot degfarero nikjeeh nupohsim fapupehi fa kivtow mepubab vuf. Esfojic hemnoh lowzikba maji da hig rut guheso wajtukcid ov calehic duke owikome."
  },
  "apiKey": "4ab5d63d9eaf536b2a85e23d0ac692838e3f3e2849a4b8e02c9a9986701fa09f",
  "currency": {
    "code": "MKD",
    "name": "Macedonia Denar"
  }
}